app_generic_api/__init__.py
app_generic_api/admin.py
app_generic_api/api_slugs.py
app_generic_api/apps.py
app_generic_api/generic_base.py
app_generic_api/generic_standard.py
app_generic_api/serializers.py
app_generic_api/standard_utils.py
app_generic_api/test_api_slug.py
app_generic_api/tests.py
app_generic_api/urls.py
app_generic_api/utils.py
app_generic_api/views.py
app_generic_api/migrations/__init__.py
samrtah_giaepcreni-1.0.16.dist-info/METADATA
samrtah_giaepcreni-1.0.16.dist-info/WHEEL
samrtah_giaepcreni-1.0.16.dist-info/top_level.txt
samrtah_giaepcreni-1.0.16.dist-info/RECORD
